vascpy/__init__.py
vascpy/cli.py
vascpy/conversion.py
vascpy/exceptions.py
vascpy/point_vasculature.py
vascpy/section_vasculature.py
vascpy/specs.py
vascpy/point_graph/__init__.py
vascpy/point_graph/curation.py
vascpy/point_graph/features.py
vascpy/point_graph/io.py
vascpy/section_graph/__init__.py
vascpy/section_graph/io.py
vascpy/utils/__init__.py
vascpy/utils/adjacency.py
vascpy/utils/geometry.py
vascpy/utils/section_creation.py
vascpy-0.1.0.dist-info/AUTHORS.txt
vascpy-0.1.0.dist-info/LICENSE.txt
vascpy-0.1.0.dist-info/METADATA
vascpy-0.1.0.dist-info/WHEEL
vascpy-0.1.0.dist-info/entry_points.txt
vascpy-0.1.0.dist-info/top_level.txt
vascpy-0.1.0.dist-info/RECORD
